{
  "model_id": "20260219_114323",
  "trained_at": "2026-02-19T11:43:23.406170",
  "artifact_path": "data/models/discipline/models/discipline_model_20260219_114323.pkl",
  "classes": [
    "Agriculture",
    "Entomology",
    "Environmental Sciences",
    "Fisheries and Aquatic",
    "Forestry and Habitat",
    "Wildlife"
  ],
  "metrics": {
    "accuracy": 0.25,
    "macro_f1": 0.1,
    "weighted_f1": 0.1,
    "evaluation_mode": "holdout",
    "validation_samples": 4
  },
  "training_summary": {
    "gold_total": 16,
    "gold_class_counts": {
      "Environmental Sciences": 3,
      "Fisheries and Aquatic": 5,
      "Forestry and Habitat": 2,
      "Wildlife": 6
    },
    "pseudo_total": 9,
    "pseudo_class_counts": {
      "Environmental Sciences": 2,
      "Wildlife": 5,
      "Entomology": 1,
      "Agriculture": 1
    },
    "pseudo_weight": 0.35,
    "positions_file": "web/data/dashboard_positions.json"
  }
}